MANIFEST.in
README.md
requirements.txt
setup.cfg
setup.py
disco/__init__.py
disco/cli.py
disco/client.py
disco/state.py
disco/api/__init__.py
disco/api/client.py
disco/api/http.py
disco/api/ratelimit.py
disco/bot/__init__.py
disco/bot/bot.py
disco/bot/command.py
disco/bot/parser.py
disco/bot/plugin.py
disco/bot/storage.py
disco/gateway/__init__.py
disco/gateway/client.py
disco/gateway/events.py
disco/gateway/ipc.py
disco/gateway/packets.py
disco/gateway/sharder.py
disco/gateway/encoding/__init__.py
disco/gateway/encoding/base.py
disco/gateway/encoding/etf.py
disco/gateway/encoding/json.py
disco/types/__init__.py
disco/types/base.py
disco/types/channel.py
disco/types/guild.py
disco/types/invite.py
disco/types/message.py
disco/types/permissions.py
disco/types/user.py
disco/types/voice.py
disco/types/webhook.py
disco/util/__init__.py
disco/util/backdoor.py
disco/util/chains.py
disco/util/config.py
disco/util/functional.py
disco/util/hashmap.py
disco/util/interactions.py
disco/util/limiter.py
disco/util/logging.py
disco/util/paginator.py
disco/util/sanitize.py
disco/util/serializer.py
disco/util/snowflake.py
disco/util/string.py
disco/util/websocket.py
disco/voice/__init__.py
disco/voice/client.py
disco/voice/opus.py
disco/voice/packets.py
disco/voice/playable.py
disco/voice/player.py
disco/voice/queue.py
disco/voice/udp.py
disco_py.egg-info/PKG-INFO
disco_py.egg-info/SOURCES.txt
disco_py.egg-info/dependency_links.txt
disco_py.egg-info/requires.txt
disco_py.egg-info/top_level.txt
examples/__init__.py
examples/basic_plugin.py
examples/music.py
tests/__init__.py
tests/imports.py
tests/utils.py
tests/api/__init__.py
tests/api/client.py
tests/api/reason.py
tests/bot/__init__.py
tests/bot/bot.py
tests/gateway/__init__.py
tests/gateway/events.py
tests/types/__init__.py
tests/types/base.py
tests/types/channel.py
tests/types/embeds.py
tests/types/types.py
tests/types/user.py
tests/util/__init__.py
tests/util/functional.py
tests/util/hashmap.py
tests/util/limiter.py
tests/voice/__init__.py
tests/voice/queue.py